{
  "cli_version": "0.4.8",
  "checkpoint_id": "faba66d688f4",
  "session_id": "ses_34e0dc314ffeu3xqecIvTwyq9q",
  "strategy": "manual-commit",
  "created_at": "2026-03-04T20:03:58.092774554Z",
  "branch": "main",
  "checkpoints_count": 0,
  "files_touched": [
    "app/app_input.go"
  ],
  "agent": "OpenCode",
  "turn_id": "269619f319b3",
  "checkpoint_transcript_start": 36,
  "transcript_lines_at_start": 36,
  "token_usage": {
    "input_tokens": 0,
    "cache_creation_tokens": 0,
    "cache_read_tokens": 0,
    "output_tokens": 0,
    "api_call_count": 0
  },
  "initial_attribution": {
    "calculated_at": "2026-03-04T20:03:57.928700502Z",
    "agent_lines": 1,
    "human_added": 118,
    "human_modified": 0,
    "human_removed": 0,
    "total_committed": 119,
    "agent_percentage": 0.8403361344537815
  }
}
