{
  "cli_version": "0.4.8",
  "checkpoint_id": "ca26c5c1ec82",
  "session_id": "ses_34451f2ecffeCwG403B5rxxvzs",
  "strategy": "manual-commit",
  "created_at": "2026-03-05T01:51:16.087682317Z",
  "branch": "plan/cli-monitoring",
  "checkpoints_count": 1,
  "files_touched": [
    "cmd/tmux_test.go"
  ],
  "agent": "OpenCode",
  "turn_id": "285633b7ea54",
  "checkpoint_transcript_start": 18,
  "transcript_lines_at_start": 18,
  "token_usage": {
    "input_tokens": 1,
    "cache_creation_tokens": 238,
    "cache_read_tokens": 69262,
    "output_tokens": 416,
    "api_call_count": 1
  },
  "initial_attribution": {
    "calculated_at": "2026-03-05T01:51:16.017925969Z",
    "agent_lines": 458,
    "human_added": 311,
    "human_modified": 0,
    "human_removed": 0,
    "total_committed": 769,
    "agent_percentage": 59.557867360208064
  }
}
