{
  "cli_version": "0.4.8",
  "checkpoint_id": "12694bf87017",
  "session_id": "ses_34db7c718ffe0lhTY1HScon0pt",
  "strategy": "manual-commit",
  "created_at": "2026-03-03T06:01:55.384257676Z",
  "branch": "plan/rename-plan-to-task",
  "checkpoints_count": 0,
  "files_touched": [
    "config/planstore/store.go",
    "session/git/plan_lifecycle.go",
    "ui/navigation_panel.go",
    "app/app_audit_test.go",
    "app/app_plan_actions_test.go",
    "config/planfsm/fsm_test.go",
    "config/taskstate/taskstate.go",
    "config/planstore/server_test.go",
    "session/instance_lifecycle.go",
    "app/app_solo_agent_test.go",
    "app/app_wave_orchestration_flow_test.go",
    "app/clickup_progress.go",
    "cmd/plan_test.go",
    "config/planfsm/fsm.go",
    "app/app_state.go",
    "config/planstore/server.go",
    "app/app_planner_signal_test.go",
    "config/planstore/sqlite.go",
    "app/app_input.go",
    "cmd/serve.go",
    "config/planfsm/signals_test.go",
    "config/planstore/http.go",
    "config/planstore/http_test.go",
    "config/planstore/migrate.go",
    "app/app_plan_completion_test.go",
    "app/clickup_progress_test.go",
    "app/fsm_test_helpers_test.go",
    "app/plan_cancel_rename_delay_test.go",
    "config/taskstate/taskstate_test.go",
    "config/planstore/sqlite_test.go",
    "app/app_plan_context_actions_test.go",
    "cmd/plan.go",
    "config/auditlog/sqlite_test.go",
    "config/planstore/embedded_test.go",
    "config/planstore/factory.go",
    "app/app.go",
    "app/app_actions.go",
    "app/app_test.go"
  ],
  "agent": "OpenCode",
  "turn_id": "c59e28aea4cb",
  "token_usage": {
    "input_tokens": 14,
    "cache_creation_tokens": 51326,
    "cache_read_tokens": 596295,
    "output_tokens": 1762,
    "api_call_count": 14
  },
  "initial_attribution": {
    "calculated_at": "2026-03-03T06:01:55.01831566Z",
    "agent_lines": 1805,
    "human_added": 307,
    "human_modified": 0,
    "human_removed": 0,
    "total_committed": 2112,
    "agent_percentage": 85.46401515151516
  }
}
